pygti/__init__.py
pygti/auth.py
pygti/const.py
pygti/exceptions.py
pygti/gti.py
pygti/schemas.py
pygti-0.9.4.dist-info/LICENSE.md
pygti-0.9.4.dist-info/METADATA
pygti-0.9.4.dist-info/WHEEL
pygti-0.9.4.dist-info/top_level.txt
pygti-0.9.4.dist-info/RECORD
