Metadata-Version: 2.1
Name: pygti
Version: 0.9.4
Summary: access public transport information in hamburg, germany.
Home-page: https://github.com/vigonotion/pygti
Author: Tom Schneider
Author-email: mail@vigonotion.com
License: Apache-2.0
Classifier: License :: OSI Approved :: Apache Software License
Classifier: Programming Language :: Python
Classifier: Programming Language :: Python :: 3
Classifier: Programming Language :: Python :: 3.6
Classifier: Programming Language :: Python :: Implementation :: CPython
Classifier: Programming Language :: Python :: Implementation :: PyPy
Requires-Python: >=3.6.0
License-File: LICENSE.md
Requires-Dist: aiohttp
Requires-Dist: voluptuous
Requires-Dist: pytz
